<jui><head version='1.0'><radiogroup></radiogroup><tabpair></tabpair></head><body><JPanel tag='root' x='182' y='101' width='320' height='400' bgAlpha='1' bgColor='892211' fillOpt='null' bgFill='bg_red_bg$png'><JPanel tag='' x='68' y='77' width='180' height='180' bgAlpha='1' bgColor='123670' fillOpt='null' bgFill='others_face_circle$png'></JPanel><JImage tag='' x='0' y='300' width='320' height='100' bgAlpha='1' bgColor='654321' fillOpt='null' bgFill='bg_black_base$png'></JImage><JPushButton tag='' x='68' y='316' width='61' height='65' label_text='消息' tpl_button='std_btn'></JPushButton><JLabel tag='nameLabel' x='51' y='25' width='220' height='36' text='我 叫 这 个 名 字' align='center' valign='middle' autoWrap='false' useStroke='true' strokeColor='e0600' strokeBlur='4' strokeStrength='4' useHtml='false' font='Microsoft YaHei' size='24' color='f3e5d2' bold='false' italic='false' underline='false' usePack='false'></JLabel><JPushButton tag='' x='126' y='316' width='61' height='65' label_text='榜单' tpl_button='std_btn'></JPushButton><JPushButton tag='' x='185' y='316' width='61' height='65' label_text='好友' tpl_button='std_btn'></JPushButton></JPanel></body></jui>